rlabs_gitlab_release_bot/__init__.py
rlabs_gitlab_release_bot/commit.py
rlabs_gitlab_release_bot/config.py
rlabs_gitlab_release_bot/directory.py
rlabs_gitlab_release_bot/error.py
rlabs_gitlab_release_bot/gitlab.py
rlabs_gitlab_release_bot/logger.py
rlabs_gitlab_release_bot/manual_test_run.py
rlabs_gitlab_release_bot/py.typed
rlabs_gitlab_release_bot/release.py
rlabs_gitlab_release_bot/release_notes.py
rlabs_gitlab_release_bot/types.py
rlabs_gitlab_release_bot/validate.py
rlabs_gitlab_release_bot-2.3.8.dist-info/METADATA
rlabs_gitlab_release_bot-2.3.8.dist-info/WHEEL
rlabs_gitlab_release_bot-2.3.8.dist-info/entry_points.txt
rlabs_gitlab_release_bot-2.3.8.dist-info/RECORD
