Metadata-Version: 2.1
Name: rlabs-gitlab-release-bot
Version: 2.3.8
Summary: 
License: LGPL-3.0-or-later
Author: RomanLabs
Author-email: rromanotero@romanlabs.com
Requires-Python: >=3.11,<4.0
Classifier: License :: OSI Approved :: GNU Lesser General Public License v3 or later (LGPLv3+)
Classifier: Programming Language :: Python :: 3
Classifier: Programming Language :: Python :: 3.11
Classifier: Programming Language :: Python :: 3.12
Requires-Dist: mypy (>=1.10.0,<2.0.0)
Requires-Dist: rich (>=13.7.1,<14.0.0)
Requires-Dist: rlabs-mini-gitlab (>=2.0.2,<3.0.0)
Requires-Dist: semver (>=3.0.2,<4.0.0)
